utils/__init__.py
utils/helpers.py
linkedin_burak-1.0.0.dist-info/METADATA
linkedin_burak-1.0.0.dist-info/WHEEL
linkedin_burak-1.0.0.dist-info/top_level.txt
linkedin_burak-1.0.0.dist-info/RECORD
