Metadata-Version: 2.1
Name: linkedin-burak
Version: 1.0.0
Summary: linkedin-burak
Author: Burak Atak
Author-email: your.email@example.com
